pdfToAudio/__init__.py
pdfToAudio/pdf_to_audio.py
pdfToAudio/tests_pdf_to_audio.py
pdfToAudio-1.0.2.dist-info/METADATA
pdfToAudio-1.0.2.dist-info/WHEEL
pdfToAudio-1.0.2.dist-info/top_level.txt
pdfToAudio-1.0.2.dist-info/RECORD
