Metadata-Version: 2.1
Name: pdfToAudio
Version: 1.0.2
Summary: This package creates audiobooks from PDF files
Home-page: https://github.com/programadriano/pdfToAudio
Author: Thiago S Adriano
Author-email: prof.thiagoadriano@gmail.com
License: MIT
Requires-Dist: gTTS ==2.2.3
Requires-Dist: pypdf ==2.4.0
